{
  "name": "Axelpay",
  "slug": "axelpay",
  "version": "v1",
  "category": "payment",
  "logoUrl": "",
  "description": "Integração oficial do Axelpay para processamento de pagamentos.",
  "status": "active",
  "configFields": [
    {
      "name": "storeId",
      "label": "ID da Loja (Store ID)",
      "type": "text",
      "required": true,
      "placeholder": "Ex: store_..."
    },
    {
      "name": "token",
      "label": "Token de API",
      "type": "password",
      "required": true,
      "placeholder": "Ex: axel_..."
    }
  ],
  "capabilities": {
    "supportsPix": true,
    "supportsCreditCard": true,
    "supportsBoleto": true,
    "supportsSubscription": false,
    "supportsSplit": false,
    "supportsRefund": true,
    "supportsWebhook": true
  }
}
